imu_fusion_py/__init__.py
imu_fusion_py/config/.DS_Store
imu_fusion_py/config/__init__.py
imu_fusion_py/config/definitions.py
imu_fusion_py/fusion_math.py
imu_fusion_py/imu_data.py
imu_fusion_py/imu_parser.py
imu_fusion_py/math_utils.py
imu_fusion_py-0.1.2.dist-info/LICENSE
imu_fusion_py-0.1.2.dist-info/METADATA
imu_fusion_py-0.1.2.dist-info/WHEEL
imu_fusion_py-0.1.2.dist-info/RECORD
